microscopestitching/__init__.py
microscopestitching/stitching.py
microscopestitching/VERSION
microscopestitching-0.2.0.dist-info/DESCRIPTION.rst
microscopestitching-0.2.0.dist-info/METADATA
microscopestitching-0.2.0.dist-info/metadata.json
microscopestitching-0.2.0.dist-info/RECORD
microscopestitching-0.2.0.dist-info/top_level.txt
microscopestitching-0.2.0.dist-info/WHEEL
