Metadata-Version: 2.0
Name: microscopestitching
Version: 0.2.0
Summary: Automatic merge/stitching of regular spaced images
Home-page: https://github.com/arve0/microscopestitching
Author: Arve Seljebu
Author-email: arve.seljebu@gmail.com
License: MIT
Keywords: microscopestitching
Platform: UNKNOWN
Classifier: Development Status :: 3 - Alpha
Classifier: Intended Audience :: Developers
Classifier: License :: OSI Approved :: MIT License
Classifier: Natural Language :: English
Classifier: Programming Language :: Python :: 3
Classifier: Programming Language :: Python :: 3.4
Requires-Dist: imreg-dft
Requires-Dist: scikit-image
Requires-Dist: numpy
Requires-Dist: joblib
